<?xml version="1.0" encoding="UTF-8" standalone="yes"?>
<MonsterBasicInfomation>
	<Monster MonsterID="10001" Name="ENEMY_NAME_10001" IsBoss="0" IsCity="0" Skill="1000111" AttackCanbeStop="1" AttackType="1" AttackRangeType="1" Speed="9" SoundID_Death="340010" Shadow_Scale="100"/>
	<Monster MonsterID="10002" Name="ENEMY_NAME_10002" IsBoss="0" IsCity="0" Skill="1000211" AttackCanbeStop="1" AttackType="1" AttackRangeType="1" Speed="12" SoundID_Death="340020" Shadow_Scale="100"/>
	<Monster MonsterID="10003" Name="ENEMY_NAME_10003" IsBoss="0" IsCity="0" Skill="1000311" AttackCanbeStop="1" AttackType="1" AttackRangeType="2" Speed="9" SoundID_Death="340030" Shadow_Scale="100"/>
	<Monster MonsterID="10004" Name="ENEMY_NAME_10004" IsBoss="0" IsCity="0" Skill="1000411" AttackCanbeStop="1" AttackType="1" AttackRangeType="2" Speed="8" SoundID_Death="340040" Shadow_Scale="100"/>
	<Monster MonsterID="10005" Name="ENEMY_NAME_10005" IsBoss="0" IsCity="0" Skill="1000511" AttackCanbeStop="1" AttackType="1" AttackRangeType="1" Speed="9" SoundID_Death="340160" Shadow_Scale="100"/>
	<Monster MonsterID="10006" Name="ENEMY_NAME_10006" IsBoss="0" IsCity="0" Skill="1000611" AttackCanbeStop="0" AttackType="1" AttackRangeType="1" Speed="8" SoundID_Death="340060" Shadow_Scale="100"/>
	<Monster MonsterID="10007" Name="ENEMY_NAME_10007" IsBoss="0" IsCity="0" Skill="1000711" AttackCanbeStop="1" AttackType="1" AttackRangeType="2" Speed="9" SoundID_Death="340070" Shadow_Scale="100"/>
	<Monster MonsterID="10008" Name="ENEMY_NAME_10008" IsBoss="0" IsCity="0" Skill="1000811" AttackCanbeStop="1" AttackType="1" AttackRangeType="1" Speed="12" SoundID_Death="340080" Shadow_Scale="100"/>
	<Monster MonsterID="10009" Name="ENEMY_NAME_10009" IsBoss="0" IsCity="0" Skill="1000911" AttackCanbeStop="1" AttackType="1" AttackRangeType="1" Speed="9" SoundID_Death="340090" Shadow_Scale="100"/>
	<Monster MonsterID="10010" Name="ENEMY_NAME_10010" IsBoss="0" IsCity="0" Skill="1001011" AttackCanbeStop="1" AttackType="1" AttackRangeType="1" Speed="11" SoundID_Death="340100" Shadow_Scale="100"/>
	<Monster MonsterID="10011" Name="ENEMY_NAME_10011" IsBoss="0" IsCity="0" Skill="1001111" AttackCanbeStop="1" AttackType="1" AttackRangeType="1" Speed="9" SoundID_Death="340110" Shadow_Scale="100"/>
	<Monster MonsterID="10012" Name="ENEMY_NAME_10012" IsBoss="0" IsCity="0" Skill="1001211" AttackCanbeStop="1" AttackType="1" AttackRangeType="2" Speed="10" SoundID_Death="340120" Shadow_Scale="100"/>
	<Monster MonsterID="10013" Name="ENEMY_NAME_10013" IsBoss="0" IsCity="0" Skill="1001311" AttackCanbeStop="1" AttackType="1" AttackRangeType="1" Speed="8" SoundID_Death="340130" Shadow_Scale="100"/>
	<Monster MonsterID="10014" Name="ENEMY_NAME_10014" IsBoss="0" IsCity="0" Skill="1001411" AttackCanbeStop="1" AttackType="1" AttackRangeType="1" Speed="12" SoundID_Death="340140" Shadow_Scale="100"/>
	<Monster MonsterID="10015" Name="ENEMY_NAME_10015" IsBoss="0" IsCity="0" Skill="1001511" AttackCanbeStop="0" AttackType="1" AttackRangeType="1" Speed="9" SoundID_Death="340150" Shadow_Scale="100"/>
	<Monster MonsterID="10016" Name="ENEMY_NAME_10016" IsBoss="0" IsCity="0" Skill="1001611" AttackCanbeStop="1" AttackType="1" AttackRangeType="1" Speed="12" SoundID_Death="340160" Shadow_Scale="100"/>
	<Monster MonsterID="10017" Name="ENEMY_NAME_10017" IsBoss="0" IsCity="0" Skill="1001711" AttackCanbeStop="1" AttackType="1" AttackRangeType="1" Speed="9" SoundID_Death="340170" Shadow_Scale="100"/>
	<Monster MonsterID="10018" Name="ENEMY_NAME_10018" IsBoss="0" IsCity="0" Skill="1001811" AttackCanbeStop="1" AttackType="1" AttackRangeType="1" Speed="8" SoundID_Death="340180" Shadow_Scale="100"/>
	<Monster MonsterID="10019" Name="ENEMY_NAME_10019" IsBoss="0" IsCity="0" Skill="1001911" AttackCanbeStop="0" AttackType="2" AttackRangeType="1" Speed="9" SoundID_Death="340190" Shadow_Scale="100"/>
	<Monster MonsterID="10020" Name="ENEMY_NAME_10020" IsBoss="0" IsCity="0" Skill="1002011" AttackCanbeStop="0" AttackType="1" AttackRangeType="2" Speed="12" SoundID_Death="340200" Shadow_Scale="100"/>
	<Monster MonsterID="10021" Name="ENEMY_NAME_10021" IsBoss="0" IsCity="0" Skill="1002111" AttackCanbeStop="1" AttackType="2" AttackRangeType="2" Speed="11" SoundID_Death="340210" Shadow_Scale="100"/>
	<Monster MonsterID="10022" Name="ENEMY_NAME_10022" IsBoss="0" IsCity="0" Skill="1002211" AttackCanbeStop="1" AttackType="1" AttackRangeType="1" Speed="10" SoundID_Death="340220" Shadow_Scale="100"/>
	<Monster MonsterID="10023" Name="ENEMY_NAME_10023" IsBoss="0" IsCity="0" Skill="1002311" AttackCanbeStop="1" AttackType="2" AttackRangeType="2" Speed="9" SoundID_Death="340230" Shadow_Scale="100"/>
	<Monster MonsterID="10024" Name="ENEMY_NAME_10024" IsBoss="0" IsCity="0" Skill="1002411" AttackCanbeStop="0" AttackType="3" AttackRangeType="1" Speed="8" SoundID_Death="340240" Shadow_Scale="100"/>
	<Monster MonsterID="10025" Name="ENEMY_NAME_10025" IsBoss="0" IsCity="0" Skill="1002511" AttackCanbeStop="0" AttackType="1" AttackRangeType="1" Speed="9" SoundID_Death="340250" Shadow_Scale="100"/>
	<Monster MonsterID="10026" Name="ENEMY_NAME_10026" IsBoss="0" IsCity="0" Skill="1002611" AttackCanbeStop="1" AttackType="1" AttackRangeType="1" Speed="10" SoundID_Death="340260" Shadow_Scale="100"/>
	<Monster MonsterID="10027" Name="ENEMY_NAME_10027" IsBoss="0" IsCity="0" Skill="1002711" AttackCanbeStop="1" AttackType="2" AttackRangeType="2" Speed="9" SoundID_Death="340270" Shadow_Scale="100"/>
	<Monster MonsterID="10028" Name="ENEMY_NAME_10028" IsBoss="0" IsCity="0" Skill="1002811" AttackCanbeStop="0" AttackType="3" AttackRangeType="1" Speed="12" SoundID_Death="340280" Shadow_Scale="100"/>
	<Monster MonsterID="10029" Name="ENEMY_NAME_10029" IsBoss="0" IsCity="0" Skill="1002911" AttackCanbeStop="0" AttackType="2" AttackRangeType="1" Speed="10" SoundID_Death="340290" Shadow_Scale="100"/>
	<Monster MonsterID="10030" Name="ENEMY_NAME_10030" IsBoss="0" IsCity="0" Skill="1003011" AttackCanbeStop="0" AttackType="1" AttackRangeType="1" Speed="9" SoundID_Death="340300" Shadow_Scale="100"/>
	<Monster MonsterID="10031" Name="ENEMY_NAME_10031" IsBoss="0" IsCity="0" Skill="1003111" AttackCanbeStop="1" AttackType="1" AttackRangeType="1" Speed="9" SoundID_Death="340010" Shadow_Scale="100"/>
	<Monster MonsterID="10032" Name="ENEMY_NAME_10032" IsBoss="0" IsCity="0" Skill="1003211" AttackCanbeStop="1" AttackType="1" AttackRangeType="1" Speed="13" SoundID_Death="340020" Shadow_Scale="100"/>
	<Monster MonsterID="10033" Name="ENEMY_NAME_10033" IsBoss="0" IsCity="0" Skill="1003311" AttackCanbeStop="1" AttackType="3" AttackRangeType="2" Speed="9" SoundID_Death="340030" Shadow_Scale="100"/>
	<Monster MonsterID="10034" Name="ENEMY_NAME_10034" IsBoss="0" IsCity="0" Skill="1003411" AttackCanbeStop="1" AttackType="2" AttackRangeType="2" Speed="8" SoundID_Death="340040" Shadow_Scale="100"/>
	<Monster MonsterID="10035" Name="ENEMY_NAME_10035" IsBoss="0" IsCity="0" Skill="1003511" AttackCanbeStop="1" AttackType="1" AttackRangeType="1" Speed="9" SoundID_Death="340050" Shadow_Scale="100"/>
	<Monster MonsterID="10036" Name="ENEMY_NAME_10036" IsBoss="0" IsCity="0" Skill="1003611" AttackCanbeStop="0" AttackType="2" AttackRangeType="1" Speed="8" SoundID_Death="340060" Shadow_Scale="100"/>
	<Monster MonsterID="10037" Name="ENEMY_NAME_10037" IsBoss="0" IsCity="0" Skill="1003711" AttackCanbeStop="1" AttackType="2" AttackRangeType="2" Speed="9" SoundID_Death="340070" Shadow_Scale="100"/>
	<Monster MonsterID="10038" Name="ENEMY_NAME_10038" IsBoss="0" IsCity="0" Skill="1003811" AttackCanbeStop="1" AttackType="1" AttackRangeType="1" Speed="13" SoundID_Death="340080" Shadow_Scale="100"/>
	<Monster MonsterID="10039" Name="ENEMY_NAME_10039" IsBoss="0" IsCity="0" Skill="1003911" AttackCanbeStop="1" AttackType="1" AttackRangeType="1" Speed="9" SoundID_Death="340090" Shadow_Scale="100"/>
	<Monster MonsterID="10040" Name="ENEMY_NAME_10040" IsBoss="0" IsCity="0" Skill="1004011" AttackCanbeStop="1" AttackType="1" AttackRangeType="1" Speed="11" SoundID_Death="340100" Shadow_Scale="100"/>
	<Monster MonsterID="10041" Name="ENEMY_NAME_10041" IsBoss="0" IsCity="0" Skill="1004111" AttackCanbeStop="1" AttackType="1" AttackRangeType="1" Speed="9" SoundID_Death="340110" Shadow_Scale="100"/>
	<Monster MonsterID="10042" Name="ENEMY_NAME_10042" IsBoss="0" IsCity="0" Skill="1004211" AttackCanbeStop="1" AttackType="2" AttackRangeType="2" Speed="10" SoundID_Death="340120" Shadow_Scale="100"/>
	<Monster MonsterID="10043" Name="ENEMY_NAME_10043" IsBoss="0" IsCity="0" Skill="1004311" AttackCanbeStop="1" AttackType="3" AttackRangeType="1" Speed="8" SoundID_Death="340130" Shadow_Scale="100"/>
	<Monster MonsterID="10044" Name="ENEMY_NAME_10044" IsBoss="0" IsCity="0" Skill="1004411" AttackCanbeStop="1" AttackType="1" AttackRangeType="1" Speed="13" SoundID_Death="340140" Shadow_Scale="100"/>
	<Monster MonsterID="10045" Name="ENEMY_NAME_10045" IsBoss="0" IsCity="0" Skill="1004511" AttackCanbeStop="0" AttackType="3" AttackRangeType="1" Speed="9" SoundID_Death="340150" Shadow_Scale="100"/>
	<Monster MonsterID="10046" Name="ENEMY_NAME_10046" IsBoss="0" IsCity="0" Skill="1004611" AttackCanbeStop="1" AttackType="1" AttackRangeType="1" Speed="12" SoundID_Death="340160" Shadow_Scale="100"/>
	<Monster MonsterID="10047" Name="ENEMY_NAME_10047" IsBoss="0" IsCity="0" Skill="1004711" AttackCanbeStop="1" AttackType="1" AttackRangeType="1" Speed="9" SoundID_Death="340170" Shadow_Scale="100"/>
	<Monster MonsterID="10048" Name="ENEMY_NAME_10048" IsBoss="0" IsCity="0" Skill="1004811" AttackCanbeStop="1" AttackType="1" AttackRangeType="1" Speed="8" SoundID_Death="340180" Shadow_Scale="100"/>
	<Monster MonsterID="10049" Name="ENEMY_NAME_10049" IsBoss="0" IsCity="0" Skill="1004911" AttackCanbeStop="0" AttackType="2" AttackRangeType="1" Speed="9" SoundID_Death="340190" Shadow_Scale="100"/>
	<Monster MonsterID="10050" Name="ENEMY_NAME_10050" IsBoss="0" IsCity="0" Skill="1005011" AttackCanbeStop="0" AttackType="3" AttackRangeType="1" Speed="13" SoundID_Death="340200" Shadow_Scale="100"/>
	<Monster MonsterID="10051" Name="ENEMY_NAME_10051" IsBoss="0" IsCity="0" Skill="1005111" AttackCanbeStop="1" AttackType="2" AttackRangeType="2" Speed="11" SoundID_Death="340210" Shadow_Scale="100"/>
	<Monster MonsterID="10052" Name="ENEMY_NAME_10052" IsBoss="0" IsCity="0" Skill="1005211" AttackCanbeStop="1" AttackType="1" AttackRangeType="1" Speed="10" SoundID_Death="340220" Shadow_Scale="100"/>
	<Monster MonsterID="10053" Name="ENEMY_NAME_10053" IsBoss="0" IsCity="0" Skill="1005311" AttackCanbeStop="1" AttackType="2" AttackRangeType="2" Speed="9" SoundID_Death="340230" Shadow_Scale="100"/>
	<Monster MonsterID="10054" Name="ENEMY_NAME_10054" IsBoss="0" IsCity="0" Skill="1005411" AttackCanbeStop="0" AttackType="3" AttackRangeType="1" Speed="8" SoundID_Death="340240" Shadow_Scale="100"/>
	<Monster MonsterID="10055" Name="ENEMY_NAME_10055" IsBoss="0" IsCity="0" Skill="1005511" AttackCanbeStop="0" AttackType="1" AttackRangeType="1" Speed="9" SoundID_Death="340250" Shadow_Scale="100"/>
	<Monster MonsterID="10056" Name="ENEMY_NAME_10056" IsBoss="0" IsCity="0" Skill="1005611" AttackCanbeStop="1" AttackType="3" AttackRangeType="1" Speed="10" SoundID_Death="340260" Shadow_Scale="100"/>
	<Monster MonsterID="10057" Name="ENEMY_NAME_10057" IsBoss="0" IsCity="0" Skill="1005711" AttackCanbeStop="1" AttackType="2" AttackRangeType="2" Speed="9" SoundID_Death="340270" Shadow_Scale="100"/>
	<Monster MonsterID="10058" Name="ENEMY_NAME_10058" IsBoss="0" IsCity="0" Skill="1005811" AttackCanbeStop="0" AttackType="3" AttackRangeType="1" Speed="13" SoundID_Death="340280" Shadow_Scale="100"/>
	<Monster MonsterID="10059" Name="ENEMY_NAME_10059" IsBoss="0" IsCity="0" Skill="1005911" AttackCanbeStop="0" AttackType="3" AttackRangeType="1" Speed="10" SoundID_Death="340290" Shadow_Scale="100"/>
	<Monster MonsterID="10061" Name="ENEMY_NAME_10061" IsBoss="0" IsCity="0" Skill="1006111" AttackCanbeStop="1" AttackType="1" AttackRangeType="1" Speed="9" SoundID_Death="340010" Shadow_Scale="100"/>
	<Monster MonsterID="10062" Name="ENEMY_NAME_10062" IsBoss="0" IsCity="0" Skill="1006211" AttackCanbeStop="1" AttackType="3" AttackRangeType="1" Speed="13" SoundID_Death="340020" Shadow_Scale="100"/>
	<Monster MonsterID="10063" Name="ENEMY_NAME_10063" IsBoss="0" IsCity="0" Skill="1006311" AttackCanbeStop="1" AttackType="3" AttackRangeType="2" Speed="9" SoundID_Death="340030" Shadow_Scale="100"/>
	<Monster MonsterID="10064" Name="ENEMY_NAME_10064" IsBoss="0" IsCity="0" Skill="1006411" AttackCanbeStop="1" AttackType="2" AttackRangeType="2" Speed="8" SoundID_Death="340040" Shadow_Scale="100"/>
	<Monster MonsterID="10065" Name="ENEMY_NAME_10065" IsBoss="0" IsCity="0" Skill="1006511" AttackCanbeStop="1" AttackType="2" AttackRangeType="1" Speed="9" SoundID_Death="340050" Shadow_Scale="100"/>
	<Monster MonsterID="10066" Name="ENEMY_NAME_10066" IsBoss="0" IsCity="0" Skill="1006611" AttackCanbeStop="0" AttackType="1" AttackRangeType="1" Speed="8" SoundID_Death="340060" Shadow_Scale="100"/>
	<Monster MonsterID="10067" Name="ENEMY_NAME_10067" IsBoss="0" IsCity="0" Skill="1006711" AttackCanbeStop="1" AttackType="2" AttackRangeType="2" Speed="9" SoundID_Death="340070" Shadow_Scale="100"/>
	<Monster MonsterID="10068" Name="ENEMY_NAME_10068" IsBoss="0" IsCity="0" Skill="1006811" AttackCanbeStop="1" AttackType="2" AttackRangeType="2" Speed="13" SoundID_Death="340080" Shadow_Scale="100"/>
	<Monster MonsterID="10069" Name="ENEMY_NAME_10069" IsBoss="0" IsCity="0" Skill="1006911" AttackCanbeStop="1" AttackType="1" AttackRangeType="1" Speed="9" SoundID_Death="340090" Shadow_Scale="100"/>
	<Monster MonsterID="10070" Name="ENEMY_NAME_10070" IsBoss="0" IsCity="0" Skill="1007011" AttackCanbeStop="1" AttackType="3" AttackRangeType="1" Speed="11" SoundID_Death="340100" Shadow_Scale="100"/>
	<Monster MonsterID="10071" Name="ENEMY_NAME_10071" IsBoss="0" IsCity="0" Skill="1007111" AttackCanbeStop="1" AttackType="1" AttackRangeType="1" Speed="9" SoundID_Death="340110" Shadow_Scale="100"/>
	<Monster MonsterID="10072" Name="ENEMY_NAME_10072" IsBoss="0" IsCity="0" Skill="1007211" AttackCanbeStop="1" AttackType="2" AttackRangeType="2" Speed="10" SoundID_Death="340120" Shadow_Scale="100"/>
	<Monster MonsterID="10073" Name="ENEMY_NAME_10073" IsBoss="0" IsCity="0" Skill="1007311" AttackCanbeStop="1" AttackType="2" AttackRangeType="2" Speed="8" SoundID_Death="340130" Shadow_Scale="100"/>
	<Monster MonsterID="10074" Name="ENEMY_NAME_10074" IsBoss="0" IsCity="0" Skill="1007411" AttackCanbeStop="1" AttackType="3" AttackRangeType="1" Speed="13" SoundID_Death="340140" Shadow_Scale="100"/>
	<Monster MonsterID="10075" Name="ENEMY_NAME_10075" IsBoss="0" IsCity="0" Skill="1007511" AttackCanbeStop="0" AttackType="1" AttackRangeType="1" Speed="9" SoundID_Death="340150" Shadow_Scale="100"/>
	<Monster MonsterID="10076" Name="ENEMY_NAME_10076" IsBoss="0" IsCity="0" Skill="1007611" AttackCanbeStop="1" AttackType="3" AttackRangeType="1" Speed="12" SoundID_Death="340160" Shadow_Scale="100"/>
	<Monster MonsterID="10077" Name="ENEMY_NAME_10077" IsBoss="0" IsCity="0" Skill="1007711" AttackCanbeStop="1" AttackType="1" AttackRangeType="1" Speed="9" SoundID_Death="340170" Shadow_Scale="100"/>
	<Monster MonsterID="10078" Name="ENEMY_NAME_10078" IsBoss="0" IsCity="0" Skill="1007811" AttackCanbeStop="1" AttackType="1" AttackRangeType="1" Speed="8" SoundID_Death="340180" Shadow_Scale="100"/>
	<Monster MonsterID="10079" Name="ENEMY_NAME_10079" IsBoss="0" IsCity="0" Skill="1007911" AttackCanbeStop="0" AttackType="2" AttackRangeType="2" Speed="9" SoundID_Death="340190" Shadow_Scale="100"/>
	<Monster MonsterID="10080" Name="ENEMY_NAME_10080" IsBoss="0" IsCity="0" Skill="1008011" AttackCanbeStop="0" AttackType="3" AttackRangeType="1" Speed="13" SoundID_Death="340200" Shadow_Scale="100"/>
	<Monster MonsterID="10081" Name="ENEMY_NAME_10081" IsBoss="0" IsCity="0" Skill="1008111" AttackCanbeStop="1" AttackType="2" AttackRangeType="2" Speed="11" SoundID_Death="340210" Shadow_Scale="100"/>
	<Monster MonsterID="10082" Name="ENEMY_NAME_10082" IsBoss="0" IsCity="0" Skill="1008211" AttackCanbeStop="1" AttackType="1" AttackRangeType="1" Speed="10" SoundID_Death="340220" Shadow_Scale="100"/>
	<Monster MonsterID="10083" Name="ENEMY_NAME_10083" IsBoss="0" IsCity="0" Skill="1008311" AttackCanbeStop="1" AttackType="2" AttackRangeType="2" Speed="9" SoundID_Death="340230" Shadow_Scale="100"/>
	<Monster MonsterID="10084" Name="ENEMY_NAME_10084" IsBoss="0" IsCity="0" Skill="1008411" AttackCanbeStop="0" AttackType="3" AttackRangeType="1" Speed="8" SoundID_Death="340240" Shadow_Scale="100"/>
	<Monster MonsterID="10085" Name="ENEMY_NAME_10085" IsBoss="0" IsCity="0" Skill="1008511" AttackCanbeStop="0" AttackType="1" AttackRangeType="1" Speed="9" SoundID_Death="340250" Shadow_Scale="100"/>
	<Monster MonsterID="10086" Name="ENEMY_NAME_10086" IsBoss="0" IsCity="0" Skill="1008611" AttackCanbeStop="0" AttackType="1" AttackRangeType="1" Speed="10" SoundID_Death="340220" Shadow_Scale="100"/>
	<Monster MonsterID="10087" Name="ENEMY_NAME_10087" IsBoss="0" IsCity="0" Skill="1008711" AttackCanbeStop="0" AttackType="3" AttackRangeType="1" Speed="12" SoundID_Death="340260" Shadow_Scale="100"/>
	<Monster MonsterID="10088" Name="ENEMY_NAME_10088" IsBoss="0" IsCity="0" Skill="1008811" AttackCanbeStop="0" AttackType="1" AttackRangeType="1" Speed="10" SoundID_Death="340250" Shadow_Scale="100"/>
	<Monster MonsterID="10089" Name="ENEMY_NAME_10089" IsBoss="0" IsCity="0" Skill="1008911" AttackCanbeStop="0" AttackType="3" AttackRangeType="2" Speed="12" SoundID_Death="340250" Shadow_Scale="100"/>
	<Monster MonsterID="10090" Name="ENEMY_NAME_10090" IsBoss="0" IsCity="0" Skill="1009011" AttackCanbeStop="0" AttackType="1" AttackRangeType="1" Speed="11" SoundID_Death="340230" Shadow_Scale="100"/>
	<Monster MonsterID="10091" Name="ENEMY_NAME_10091" IsBoss="0" IsCity="0" Skill="1009111" AttackCanbeStop="0" AttackType="3" AttackRangeType="1" Speed="12" SoundID_Death="340240" Shadow_Scale="100"/>
	<Monster MonsterID="10092" Name="ENEMY_NAME_10092" IsBoss="0" IsCity="0" Skill="1009211" AttackCanbeStop="0" AttackType="2" AttackRangeType="2" Speed="12" SoundID_Death="340220" Shadow_Scale="100"/>
	<Monster MonsterID="10093" Name="ENEMY_NAME_10093" IsBoss="0" IsCity="0" Skill="1009311" AttackCanbeStop="0" AttackType="2" AttackRangeType="2" Speed="11" SoundID_Death="340230" Shadow_Scale="100"/>
	<Monster MonsterID="10094" Name="ENEMY_NAME_10094" IsBoss="0" IsCity="0" Skill="1009411" AttackCanbeStop="0" AttackType="1" AttackRangeType="1" Speed="10" SoundID_Death="340060" Shadow_Scale="100"/>
	<Monster MonsterID="10095" Name="ENEMY_NAME_10095" IsBoss="0" IsCity="0" Skill="1009511" AttackCanbeStop="0" AttackType="1" AttackRangeType="1" Speed="11" SoundID_Death="340110" Shadow_Scale="100"/>
	<Monster MonsterID="10096" Name="ENEMY_NAME_10096" IsBoss="0" IsCity="0" Skill="1009611" AttackCanbeStop="0" AttackType="1" AttackRangeType="1" Speed="11" SoundID_Death="340110" Shadow_Scale="100"/>
	<Monster MonsterID="10097" Name="ENEMY_NAME_10097" IsBoss="0" IsCity="0" Skill="1009711" AttackCanbeStop="0" AttackType="1" AttackRangeType="1" Speed="9" SoundID_Death="340060" Shadow_Scale="100"/>
	<Monster MonsterID="10098" Name="ENEMY_NAME_10098" IsBoss="0" IsCity="0" Skill="1009811" AttackCanbeStop="0" AttackType="1" AttackRangeType="1" Speed="12" SoundID_Death="340080" Shadow_Scale="100"/>
	<Monster MonsterID="10099" Name="ENEMY_NAME_10099" IsBoss="0" IsCity="0" Skill="1009911" AttackCanbeStop="0" AttackType="1" AttackRangeType="1" Speed="8" SoundID_Death="340060" Shadow_Scale="100"/>
	<Monster MonsterID="10100" Name="ENEMY_NAME_10100" IsBoss="0" IsCity="0" Skill="1010011" AttackCanbeStop="0" AttackType="1" AttackRangeType="1" Speed="10" SoundID_Death="340050" Shadow_Scale="100"/>
	<Monster MonsterID="10101" Name="ENEMY_NAME_10101" IsBoss="0" IsCity="0" Skill="1010111" AttackCanbeStop="0" AttackType="2" AttackRangeType="2" Speed="10" SoundID_Death="340180" Shadow_Scale="100"/>
	<Monster MonsterID="10102" Name="ENEMY_NAME_10102" IsBoss="0" IsCity="0" Skill="1010211" AttackCanbeStop="0" AttackType="1" AttackRangeType="1" Speed="11" SoundID_Death="340190" Shadow_Scale="100"/>
	<Monster MonsterID="10103" Name="ENEMY_NAME_10103" IsBoss="0" IsCity="0" Skill="1010311" AttackCanbeStop="0" AttackType="2" AttackRangeType="2" Speed="11" SoundID_Death="340200" Shadow_Scale="100"/>
	<Monster MonsterID="10104" Name="ENEMY_NAME_10104" IsBoss="0" IsCity="0" Skill="1010411" AttackCanbeStop="0" AttackType="1" AttackRangeType="1" Speed="11" SoundID_Death="340260" Shadow_Scale="100"/>
	<Monster MonsterID="10105" Name="ENEMY_NAME_10105" IsBoss="0" IsCity="0" Skill="1010511" AttackCanbeStop="0" AttackType="2" AttackRangeType="2" Speed="10" SoundID_Death="340260" Shadow_Scale="100"/>
	<Monster MonsterID="10106" Name="ENEMY_NAME_10106" IsBoss="0" IsCity="0" Skill="1010611" AttackCanbeStop="0" AttackType="3" AttackRangeType="1" Speed="10" SoundID_Death="340200" Shadow_Scale="100"/>
	<Monster MonsterID="10107" Name="ENEMY_NAME_10107" IsBoss="0" IsCity="0" Skill="1010711" AttackCanbeStop="0" AttackType="3" AttackRangeType="1" Speed="12" SoundID_Death="340170" Shadow_Scale="100"/>
	<Monster MonsterID="11001" Name="ENEMY_NAME_11001" IsBoss="0" IsCity="0" Skill="1100111" AttackCanbeStop="0" AttackType="2" AttackRangeType="2" Speed="9" SoundID_Death="340270" Shadow_Scale="100"/>
	<Monster MonsterID="11002" Name="ENEMY_NAME_11002" IsBoss="0" IsCity="0" Skill="1100211" AttackCanbeStop="0" AttackType="1" AttackRangeType="1" Speed="12" SoundID_Death="340270" Shadow_Scale="100"/>
	<Monster MonsterID="11003" Name="ENEMY_NAME_11003" IsBoss="0" IsCity="0" Skill="1100311" AttackCanbeStop="0" AttackType="1" AttackRangeType="2" Speed="11" SoundID_Death="340270" Shadow_Scale="100"/>
	<Monster MonsterID="11004" Name="ENEMY_NAME_11004" IsBoss="0" IsCity="0" Skill="1100411" AttackCanbeStop="0" AttackType="1" AttackRangeType="1" Speed="9" SoundID_Death="340200" Shadow_Scale="100"/>
	<Monster MonsterID="11005" Name="ENEMY_NAME_11005" IsBoss="0" IsCity="0" Skill="1100511" AttackCanbeStop="0" AttackType="2" AttackRangeType="2" Speed="12" SoundID_Death="340140" Shadow_Scale="100"/>
	<Monster MonsterID="11006" Name="ENEMY_NAME_11006" IsBoss="0" IsCity="0" Skill="1100611" AttackCanbeStop="0" AttackType="1" AttackRangeType="1" Speed="11" SoundID_Death="340050" Shadow_Scale="100"/>
	<Monster MonsterID="19001" Name="ENEMY_NAME_19001" IsBoss="1" IsCity="0" Skill="1900111;1900121" AttackCanbeStop="0" AttackType="0" AttackRangeType="1" Speed="8" SoundID_Death="330012" Shadow_Scale="150"/>
	<Monster MonsterID="19002" Name="ENEMY_NAME_19002" IsBoss="1" IsCity="0" Skill="1900211;1900221" AttackCanbeStop="0" AttackType="0" AttackRangeType="1" Speed="0" SoundID_Death="330022" Shadow_Scale="250"/>
	<Monster MonsterID="19003" Name="ENEMY_NAME_19003" IsBoss="1" IsCity="0" Skill="1900311;1900321;1900331" AttackCanbeStop="0" AttackType="0" AttackRangeType="1" Speed="11" SoundID_Death="330033" Shadow_Scale="250"/>
	<Monster MonsterID="19004" Name="ENEMY_NAME_19004" IsBoss="1" IsCity="0" Skill="1900411;1900421;1900431" AttackCanbeStop="0" AttackType="0" AttackRangeType="1" Speed="9" SoundID_Death="330043" Shadow_Scale="150"/>
	<Monster MonsterID="19005" Name="ENEMY_NAME_19005" IsBoss="1" IsCity="0" Skill="1900511;1900521;1900531" AttackCanbeStop="0" AttackType="0" AttackRangeType="1" Speed="10" SoundID_Death="330053" Shadow_Scale="200"/>
	<Monster MonsterID="19006" Name="ENEMY_NAME_19006" IsBoss="1" IsCity="0" Skill="1900611;1900621;1900631" AttackCanbeStop="0" AttackType="0" AttackRangeType="1" Speed="9" SoundID_Death="330063" Shadow_Scale="200"/>
	<Monster MonsterID="19007" Name="ENEMY_NAME_19007" IsBoss="1" IsCity="0" Skill="1900711;1900721;1900731" AttackCanbeStop="0" AttackType="0" AttackRangeType="1" Speed="11" SoundID_Death="330073" Shadow_Scale="200"/>
	<Monster MonsterID="19008" Name="ENEMY_NAME_19008" IsBoss="1" IsCity="0" Skill="1900811;1900821;1900831" AttackCanbeStop="0" AttackType="0" AttackRangeType="1" Speed="10" SoundID_Death="330012" Shadow_Scale="150"/>
	<Monster MonsterID="19009" Name="ENEMY_NAME_19009" IsBoss="1" IsCity="0" Skill="1900911;1900921;1900931;1900941" AttackCanbeStop="0" AttackType="0" AttackRangeType="1" Speed="11" SoundID_Death="330093" Shadow_Scale="250"/>
	<Monster MonsterID="19010" Name="ENEMY_NAME_19010" IsBoss="1" IsCity="0" Skill="1901011;1901021;1901031;1901041;1901051" AttackCanbeStop="0" AttackType="0" AttackRangeType="1" Speed="10" SoundID_Death="330105" Shadow_Scale="100"/>
	<Monster MonsterID="19011" Name="ENEMY_NAME_19011" IsBoss="1" IsCity="0" Skill="1901111;1901121;1901131" AttackCanbeStop="0" AttackType="0" AttackRangeType="1" Speed="9" SoundID_Death="330063" Shadow_Scale="300"/>
	<Monster MonsterID="19012" Name="ENEMY_NAME_19012" IsBoss="1" IsCity="0" Skill="1901211;1901221;1901231" AttackCanbeStop="0" AttackType="0" AttackRangeType="1" Speed="11" SoundID_Death="330123" Shadow_Scale="150"/>
	<Monster MonsterID="19013" Name="ENEMY_NAME_19013" IsBoss="1" IsCity="0" Skill="1901311;1901321;1901331;1901341" AttackCanbeStop="0" AttackType="0" AttackRangeType="1" Speed="10" SoundID_Death="330043" Shadow_Scale="150"/>
	<Monster MonsterID="19022" Name="ENEMY_NAME_19022" IsBoss="1" IsCity="0" Skill="1902211;1902221;1902231;1902241" AttackCanbeStop="0" AttackType="0" AttackRangeType="1" Speed="12" SoundID_Death="330224" Shadow_Scale="250"/>
	<Monster MonsterID="19014" Name="ENEMY_NAME_19014" IsBoss="1" IsCity="0" Skill="1901411;1901421;1901431;1901441;1901451" AttackCanbeStop="0" AttackType="0" AttackRangeType="1" Speed="11" SoundID_Death="330145" Shadow_Scale="300"/>
	<Monster MonsterID="19015" Name="ENEMY_NAME_19015" IsBoss="1" IsCity="0" Skill="1901511;1901521;1901531" AttackCanbeStop="0" AttackType="0" AttackRangeType="1" Speed="9" SoundID_Death="330153" Shadow_Scale="200"/>
	<Monster MonsterID="19016" Name="ENEMY_NAME_19016" IsBoss="1" IsCity="0" Skill="1901611;1901621;1901631" AttackCanbeStop="0" AttackType="0" AttackRangeType="1" Speed="11" SoundID_Death="330163" Shadow_Scale="200"/>
	<Monster MonsterID="19017" Name="ENEMY_NAME_19017" IsBoss="1" IsCity="0" Skill="1901711;1901721;1901731;1901741" AttackCanbeStop="0" AttackType="0" AttackRangeType="1" Speed="12" SoundID_Death="330033" Shadow_Scale="250"/>
	<Monster MonsterID="19018" Name="ENEMY_NAME_19018" IsBoss="1" IsCity="0" Skill="1901811;1901821;1901831;1901841" AttackCanbeStop="0" AttackType="0" AttackRangeType="1" Speed="10" SoundID_Death="330163" Shadow_Scale="200"/>
	<Monster MonsterID="19019" Name="ENEMY_NAME_19019" IsBoss="1" IsCity="0" Skill="1901911;1901921;1901931;1901941" AttackCanbeStop="0" AttackType="0" AttackRangeType="1" Speed="11" SoundID_Death="330123" Shadow_Scale="200"/>
	<Monster MonsterID="19023" Name="ENEMY_NAME_19023" IsBoss="1" IsCity="0" Skill="1902311;1902321;1902331;1902341;1902351" AttackCanbeStop="0" AttackType="0" AttackRangeType="1" Speed="12" SoundID_Death="330224" Shadow_Scale="250"/>
	<Monster MonsterID="19024" Name="ENEMY_NAME_19024" IsBoss="1" IsCity="0" Skill="1902411;1902421;1902431;1902441" AttackCanbeStop="0" AttackType="0" AttackRangeType="1" Speed="10" SoundID_Death="335054" Shadow_Scale="100"/>
	<Monster MonsterID="19501" Name="ENEMY_NAME_19501" IsBoss="1" IsCity="0" Skill="1950111;1950121;1950131;1950141" AttackCanbeStop="0" AttackType="0" AttackRangeType="1" Speed="12" SoundID_Death="335014" Shadow_Scale="100"/>
	<Monster MonsterID="19502" Name="ENEMY_NAME_19502" IsBoss="1" IsCity="0" Skill="1950211;1950221;1950231;1950241" AttackCanbeStop="0" AttackType="0" AttackRangeType="1" Speed="12" SoundID_Death="335024" Shadow_Scale="100"/>
	<Monster MonsterID="19503" Name="ENEMY_NAME_19503" IsBoss="1" IsCity="0" Skill="1950311;1950321;1950331;1950341" AttackCanbeStop="0" AttackType="0" AttackRangeType="1" Speed="12" SoundID_Death="330145" Shadow_Scale="100"/>
	<Monster MonsterID="19504" Name="ENEMY_NAME_19504" IsBoss="1" IsCity="0" Skill="1950411;1950421;1950431;1950441;1950451" AttackCanbeStop="0" AttackType="0" AttackRangeType="1" Speed="13" SoundID_Death="335045" Shadow_Scale="100"/>
	<Monster MonsterID="19505" Name="ENEMY_NAME_19505" IsBoss="1" IsCity="0" Skill="1950511;1950521;1950531;1950541" AttackCanbeStop="0" AttackType="0" AttackRangeType="1" Speed="12" SoundID_Death="335054" Shadow_Scale="100"/>
	<Monster MonsterID="19506" Name="ENEMY_NAME_19506" IsBoss="1" IsCity="0" Skill="1950611;1950621;1950631;1950641" AttackCanbeStop="0" AttackType="0" AttackRangeType="1" Speed="12" SoundID_Death="330105" Shadow_Scale="100"/>
	<Monster MonsterID="19507" Name="ENEMY_NAME_19507" IsBoss="1" IsCity="0" Skill="1950711;1950721;1950731;1950741" AttackCanbeStop="0" AttackType="0" AttackRangeType="1" Speed="12" SoundID_Death="335054" Shadow_Scale="100"/>
	<Monster MonsterID="19508" Name="ENEMY_NAME_19508" IsBoss="1" IsCity="0" Skill="1950811;1950821;1950831;1950841;1950851" AttackCanbeStop="0" AttackType="0" AttackRangeType="1" Speed="12" SoundID_Death="335083" Shadow_Scale="200"/>
	<Monster MonsterID="19509" Name="ENEMY_NAME_19509" IsBoss="1" IsCity="0" Skill="1950911;1950921;1950931;1950941" AttackCanbeStop="0" AttackType="0" AttackRangeType="1" Speed="9" SoundID_Death="330224" Shadow_Scale="200"/>
	<Monster MonsterID="19510" Name="ENEMY_NAME_19510" IsBoss="1" IsCity="0" Skill="1951011;1951021;1951031" AttackCanbeStop="0" AttackType="0" AttackRangeType="1" Speed="9" SoundID_Death="330224" Shadow_Scale="200"/>
	<Monster MonsterID="19511" Name="ENEMY_NAME_19511" IsBoss="1" IsCity="0" Skill="1951111;1951121;1951131;1951141" AttackCanbeStop="0" AttackType="0" AttackRangeType="1" Speed="9" SoundID_Death="335115" Shadow_Scale="200"/>
	<Monster MonsterID="19512" Name="ENEMY_NAME_19512" IsBoss="1" IsCity="0" Skill="1951211;1951221;1951231l;1951241" AttackCanbeStop="0" AttackType="0" AttackRangeType="1" Speed="9" SoundID_Death="3211009" Shadow_Scale="100"/>
	<Monster MonsterID="19999" Name="ENEMY_NAME_19999" IsBoss="1" IsCity="0" Skill="1999911;1999921;1999931;1999941" AttackCanbeStop="0" AttackType="0" AttackRangeType="1" Speed="0" Shadow_Scale="100"/>
	<Monster MonsterID="16001" Name="ENEMY_NAME_16001" IsBoss="0" IsCity="1" AttackCanbeStop="0" AttackType="0" AttackRangeType="0" Speed="0" SoundID_Death="311600" Shadow_Scale="100"/>
</MonsterBasicInfomation>